mosaic_client/__init__.py
mosaic_client/epix.py
mosaic_client/gpas.py
mosaic_client/helper.py
mosaic_client/model.py
mosaic_client/schema.py
mosaic_client-0.1.0.dist-info/WHEEL
mosaic_client-0.1.0.dist-info/METADATA
mosaic_client-0.1.0.dist-info/RECORD
