Metadata-Version: 2.1
Name: mosaic-client
Version: 0.1.0
Summary: Easy consumption of SOAP interfaces provided by E-PIX and gPAS of the MOSAIC suite
License: MIT
Author: Maximilian Jugl
Author-email: Maximilian.Jugl@medizin.uni-leipzig.de
Maintainer: Maximilian Jugl
Maintainer-email: Maximilian.Jugl@medizin.uni-leipzig.de
Requires-Python: >=3.10,<4.0
Classifier: Development Status :: 4 - Beta
Classifier: Intended Audience :: Developers
Classifier: Intended Audience :: Healthcare Industry
Classifier: Intended Audience :: Information Technology
Classifier: Intended Audience :: Science/Research
Classifier: License :: OSI Approved :: MIT License
Classifier: Natural Language :: English
Classifier: Operating System :: OS Independent
Classifier: Programming Language :: Python :: 3
Classifier: Programming Language :: Python :: 3.10
Classifier: Topic :: Scientific/Engineering :: Medical Science Apps.
Classifier: Typing :: Typed
Requires-Dist: marshmallow (>=3.16.0,<4.0.0)
Requires-Dist: zeep (>=4.1.0,<5.0.0)
Project-URL: Documentation, https://pprl.gitlab.io/mosaic-client-python/
